datasette_youtube_embed/__init__.py
datasette_youtube_embed/static/lite-yt-embed.css
datasette_youtube_embed/static/lite-yt-embed.js
datasette_youtube_embed-0.1.dist-info/LICENSE
datasette_youtube_embed-0.1.dist-info/METADATA
datasette_youtube_embed-0.1.dist-info/WHEEL
datasette_youtube_embed-0.1.dist-info/entry_points.txt
datasette_youtube_embed-0.1.dist-info/top_level.txt
datasette_youtube_embed-0.1.dist-info/RECORD
