Metadata-Version: 2.1
Name: datasette-youtube-embed
Version: 0.1
Summary: Turn YouTube URLs into embedded players in Datasette
Home-page: https://github.com/simonw/datasette-youtube-embed
Author: Simon Willison
License: Apache License, Version 2.0
Project-URL: Issues, https://github.com/simonw/datasette-youtube-embed/issues
Project-URL: CI, https://github.com/simonw/datasette-youtube-embed/actions
Project-URL: Changelog, https://github.com/simonw/datasette-youtube-embed/releases
Classifier: Framework :: Datasette
Classifier: License :: OSI Approved :: Apache Software License
Requires-Python: >=3.7
License-File: LICENSE
Requires-Dist: datasette
Provides-Extra: test
Requires-Dist: pytest ; extra == 'test'
Requires-Dist: pytest-asyncio ; extra == 'test'
